sle/__init__.py
sle/constants.py
sle/slet.py
sle/datatypes/__init__.py
sle/datatypes/bind.py
sle/datatypes/cltu_pdu.py
sle/datatypes/cltu_structure.py
sle/datatypes/common.py
sle/datatypes/pdu.py
sle/datatypes/raf_pdu.py
sle/datatypes/raf_structure.py
sle/datatypes/rcf_pdu.py
sle/datatypes/rcf_structure.py
sle/datatypes/security.py
sle/datatypes/service_instance.py
sle/proxy/__init__.py
sle/proxy/authentication.py
sle/proxy/encoding.py
sle/proxy/transport.py
sle/service/__init__.py
sle/service/base.py
sle/service/cltu.py
sle/service/raf.py
sle/service/rcf.py
sle-3.0.1.dist-info/LICENSE.txt
sle-3.0.1.dist-info/METADATA
sle-3.0.1.dist-info/WHEEL
sle-3.0.1.dist-info/entry_points.txt
sle-3.0.1.dist-info/top_level.txt
sle-3.0.1.dist-info/RECORD
