Metadata-Version: 2.1
Name: sle
Version: 3.0.1
Summary: CCSDS Space Link Extension (SLE) Protocol
Author-email: LibreCube <info@librecube.org>
License: MIT License
Project-URL: source, https://gitlab.com/librecube/lib/python-sle
License-File: LICENSE.txt
Requires-Dist: pyasn1 ==0.4.8
Requires-Dist: pyYAML
